iotilegateway/__init__.py
iotilegateway/device.py
iotilegateway/gateway.py
iotilegateway/main.py
iotilegateway/supervisor/__init__.py
iotilegateway/supervisor/client.py
iotilegateway/supervisor/main.py
iotilegateway/supervisor/send_rpc.py
iotilegateway/supervisor/server.py
iotilegateway/supervisor/service_manager.py
iotilegateway/supervisor/service_tile.py
iotilegateway/supervisor/states.py
iotilegateway/supervisor/protocol/__init__.py
iotilegateway/supervisor/protocol/messages.py
iotilegateway/supervisor/protocol/operations.py
iotile_gateway-3.1.0.dist-info/LICENSE.md
iotile_gateway-3.1.0.dist-info/METADATA
iotile_gateway-3.1.0.dist-info/WHEEL
iotile_gateway-3.1.0.dist-info/entry_points.txt
iotile_gateway-3.1.0.dist-info/top_level.txt
iotile_gateway-3.1.0.dist-info/RECORD
