Metadata-Version: 2.1
Name: iotile-gateway
Version: 3.1.0
Summary: IOTile Core Tools
Home-page: https://github.com/iotile/coretools/iotilecore
Author: Arch
Author-email: info@arch-iot.com
License: LGPLv3
Keywords: iotile,arch,embedded,hardware
Platform: UNKNOWN
Classifier: Programming Language :: Python
Classifier: Development Status :: 5 - Production/Stable
Classifier: License :: OSI Approved :: GNU Library or Lesser General Public License (LGPL)
Classifier: Operating System :: OS Independent
Classifier: Programming Language :: Python :: 3
Classifier: Programming Language :: Python :: 3.7
Classifier: Programming Language :: Python :: 3.8
Classifier: Programming Language :: Python :: 3.9
Classifier: Topic :: Software Development :: Libraries :: Python Modules
Requires-Python: >=3.7,<4
Requires-Dist: iotile-core (>=5.2)
Requires-Dist: iotile-transport-websocket (>=3.2.0)
Requires-Dist: msgpack (>=1)
